CHANGES.txt
LICENSE.txt
README.txt
docunv.py
manifest.mako
pyunv.tmproj
setup.py
docs/INTRO.txt
pyunv/__init__.py
pyunv/csvwriter.py
pyunv/manifest.py
pyunv/reader.py
pyunv/universe.py
pyunv.egg-info/PKG-INFO
pyunv.egg-info/SOURCES.txt
pyunv.egg-info/dependency_links.txt
pyunv.egg-info/not-zip-safe
pyunv.egg-info/requires.txt
pyunv.egg-info/top_level.txt
tests/__init__.py
tests/test_reader.py
tests/universes/singlejoin-gte.unv
tests/universes/singlejoin-lt-1to1-shortcut.unv
tests/universes/singlejoin-lt-1to1.unv
tests/universes/singlejoin-ne.unv
tests/universes/twojoins.unv
tests/universes/universe_xir2.pdf
tests/universes/universe_xir2.unv
tests/universes/universe_xir2_README.txt