Metadata-Version: 1.1
Name: pyunv
Version: 0.2.4
Summary: Parse SAP BusinessObjects universe (*.unv) files
Home-page: http://code.google.com/p/pyunv/
Author: David Peckham
Author-email: dave.peckham@me.com
License: LGPL
Download-URL: http://code.google.com/p/pyunv/downloads/list
Keywords: BusinessObjects,SAP,universe,unv
Platform: Many
Classifier: Development Status :: 2 - Pre-Alpha
Classifier: Environment :: Other Environment
Classifier: Intended Audience :: Developers
Classifier: License :: OSI Approved :: GNU Library or Lesser General Public License (LGPL)
Classifier: Natural Language :: English
Classifier: Operating System :: OS Independent
Classifier: Programming Language :: Python
Classifier: Topic :: Software Development :: Libraries :: Python Modules
Provides: pyunv
